just_update_arch/__init__.py
just_update_arch/cli.py
just_update_arch-0.1.1.dist-info/LICENSE.md
just_update_arch-0.1.1.dist-info/METADATA
just_update_arch-0.1.1.dist-info/WHEEL
just_update_arch-0.1.1.dist-info/entry_points.txt
just_update_arch-0.1.1.dist-info/top_level.txt
just_update_arch-0.1.1.dist-info/RECORD
