Metadata-Version: 2.1
Name: just-update-arch
Version: 0.1.1
Summary: Updates installed AUR packages.
Home-page: https://github.com/MolassesLover/JustUpdateArch
Author: MolassesLover
Author-email: 60114762+MolassesLover@users.noreply.github.com
License: GNU General Public License v3.0
License-File: LICENSE.md
Requires-Dist: colorama
